buildarr_jellyseerr/__init__.py
buildarr_jellyseerr/api.py
buildarr_jellyseerr/cli.py
buildarr_jellyseerr/config/__init__.py
buildarr_jellyseerr/config/settings/__init__.py
buildarr_jellyseerr/config/settings/general.py
buildarr_jellyseerr/config/settings/jellyfin.py
buildarr_jellyseerr/config/settings/notifications/__init__.py
buildarr_jellyseerr/config/settings/notifications/base.py
buildarr_jellyseerr/config/settings/notifications/discord.py
buildarr_jellyseerr/config/settings/notifications/email.py
buildarr_jellyseerr/config/settings/notifications/gotify.py
buildarr_jellyseerr/config/settings/notifications/lunasea.py
buildarr_jellyseerr/config/settings/notifications/notification_types.py
buildarr_jellyseerr/config/settings/notifications/pushbullet.py
buildarr_jellyseerr/config/settings/notifications/pushover.py
buildarr_jellyseerr/config/settings/notifications/slack.py
buildarr_jellyseerr/config/settings/notifications/telegram.py
buildarr_jellyseerr/config/settings/notifications/webhook.py
buildarr_jellyseerr/config/settings/notifications/webpush.py
buildarr_jellyseerr/config/settings/services/__init__.py
buildarr_jellyseerr/config/settings/services/base.py
buildarr_jellyseerr/config/settings/services/radarr.py
buildarr_jellyseerr/config/settings/services/sonarr.py
buildarr_jellyseerr/config/settings/users.py
buildarr_jellyseerr/config/types.py
buildarr_jellyseerr/exceptions.py
buildarr_jellyseerr/manager.py
buildarr_jellyseerr/plugin.py
buildarr_jellyseerr/py.typed
buildarr_jellyseerr/secrets.py
buildarr_jellyseerr/types.py
buildarr_jellyseerr-0.3.2.dist-info/LICENSE
buildarr_jellyseerr-0.3.2.dist-info/METADATA
buildarr_jellyseerr-0.3.2.dist-info/WHEEL
buildarr_jellyseerr-0.3.2.dist-info/entry_points.txt
buildarr_jellyseerr-0.3.2.dist-info/RECORD
